Metadata-Version: 2.1
Name: duprem
Version: 0.0.1
Summary: remove duplicates from list
Home-page: 
Author: Aditya Gadre
Author-email: coderzdevs@gmail.com
License: MIT
Keywords: duprem
Classifier: Development Status :: 5 - Production/Stable
Classifier: Intended Audience :: Education
Classifier: Operating System :: Microsoft :: Windows :: Windows 10
Classifier: License :: OSI Approved :: MIT License
Classifier: Programming Language :: Python :: 3
License-File: LICENCE.txt
